redis_reservation/__init__.py
redis_reservation-1.0.1.dist-info/LICENSE
redis_reservation-1.0.1.dist-info/METADATA
redis_reservation-1.0.1.dist-info/WHEEL
redis_reservation-1.0.1.dist-info/top_level.txt
redis_reservation-1.0.1.dist-info/RECORD
