Metadata-Version: 2.1
Name: redis-reservation
Version: 1.0.1
Summary: Resource reservation (locking) libraries using a Redis backend, with customizable timeouts and keep-alive support.
Home-page: https://github.com/Clever/python-redis-reservation
Author: Clever (https://clever.com)
Author-email: tech-notify@clever.com
License: Apache License 2.0
Platform: UNKNOWN
License-File: LICENSE
Requires-Dist: redis (==3.0.1)
Requires-Dist: kayvee (>=3.0.0)
Requires-Dist: future (==0.18.2)
